Workbook

Sheet README
A1: ML ENGINEER / SENIOR DS — INTERVIEW PREP
A3: Two trackers. That's it.
A5: Tracker 1: LLM & ML Learning | B5: All theory + math + code in one row per topic. Strict prerequisite order — walk top to bottom. Stages 0 → 16, from basics to advanced. Covers transformer internals, attention, fine-tuning, RLHF/DPO, quantization, inference, recsys, classical ML, stats, safety/red-teaming, agents/tool-use, and company-specific prep.
A6: Tracker 2: DSA + System Design + Projects | B6: Coding patterns, ML system design walkthroughs, project defenses, behavioral STAR stories, SQL. No strict order — pick anything you need.
A8: Daily rhythm | B8: 1 hour/day. Alternate: Mon/Wed/Fri = Tracker 1 (LLM theory). Tue/Thu/Sat = Tracker 2 (DSA + projects + system design). Adjust to taste.
A9: Each row in Tracker 1 | B9: Self-contained: read the Theory column → answer the math questions → implement the code task → mark Done. One row = ~1-2 hours.
A10: Each row in Tracker 2 | B10: One DSA pattern, one system design, one project Q&A, or one STAR story. ~1 hour each.
A12: Supporting sheets (reference, not trackers)
A13: Dashboard | B13: Auto-counts progress across both trackers.
A14: Formulas | B14: All ⭐⭐⭐ formulas to memorize. Re-write from memory monthly.
A15: Mocks | B15: 11 mocks to schedule on Pramp / Interviewing.io.
A16: Applications | B16: Track every job applied. 4 apply days built in.
A18: How to start
A19: Day 1 | B19: Open Tracker 1. Start at step 0.1. If basics feel solid, skip to your honest first weak point. Mark Status = In Progress, finish the row, mark Done.
A20: Week 1 target | B20: Tracker 1: complete 3-4 rows. Tracker 2: solve 3 DSA problems + draft 2 STAR stories.
A21: Don't change the plan for 30 days. | B21: Re-planning is procrastination. Execute first, adjust after a month.

Sheet Tracker 1 — LLM Learning
A1: # | B1: Stage | C1: Topic | D1: Theory: read & answer | E1: Math: derive on paper | F1: Code: implement | G1: Deliverable | H1: Hrs | I1: Status | J1: Confidence (1-5) | K1: Notes
A2: 1 | B2: Stage 0 — Math & ML Prereqs | C2: Linear algebra refresh | D2: Matmul, dot product, vector/matrix norms, eigenvalues. Read 3Blue1Brown Essence of LA chapters 1-7 if rusty. | E2: — | F2: Numpy: implement matmul from scratch (3 nested loops). Verify vs np.matmul on random 8×8. | G2: Notes + matmul.py | H2: 2 | I2: Not Started | J2: 1
A3: 2 | B3: Stage 0 — Math & ML Prereqs | C3: Probability + MLE | D3: Bayes theorem, Gaussian, MLE vs MAP. Why MLE = minimize neg log likelihood. | E3: Derive MLE for a Gaussian: estimate μ, σ² from n samples. Show MLE σ² is biased. | F3: — | G3: Paper derivation photographed | H3: 2 | I3: Not Started | J3: 1
A4: 3 | B4: Stage 0 — Math & ML Prereqs | C4: Calculus / chain rule | D4: Partial derivatives, multivariate chain rule. Practice 3 deep chain-rule problems. | E4: Compute ∂L/∂W for L = ||Wx − y||² by chain rule. | F4: — | G4: 3 worked problems | H4: 1 | I4: Not Started | J4: 1
A5: 4 | B5: Stage 0 — Math & ML Prereqs | C5: Logistic Regression | D5: What LR is. Sigmoid. Cross-entropy as MLE under Bernoulli. Why L2 helps. Platt scaling vs isotonic. | E5: Derive MLE → CE loss. Derive ∂CE/∂w. Show L2 regularization geometry. | F5: Numpy LR on a 2D dataset (no sklearn). Forward + backward + SGD. | G5: Paper derivation + lr.py | H5: 2 | I5: Not Started | J5: 1
A6: 5 | B6: Stage 0 — Math & ML Prereqs | C6: Bias-variance + regularization | D6: Bias-variance tradeoff. Why L1 gives sparsity, L2 doesn't. Nested CV. | E6: Derive MSE = Bias² + Variance + Noise. Geometric argument for L1 vs L2. | F6: — | G6: Paper derivation | H6: 1 | I6: Not Started | J6: 1
A7: 6 | B7: Stage 0 — Math & ML Prereqs | C7: Backprop for 2-layer net (numpy) | D7: Forward pass = function composition. Backward pass = chain rule reversed. | E7: Write all gradients on paper for a 2-layer MLP with ReLU. | F7: Numpy only: forward + backward + SGD on XOR. Verify grads match torch.autograd. | G7: backprop_numpy.py + XOR training curve | H7: 2 | I7: Not Started | J7: 1
A8: 7 | B8: Stage 0 — Math & ML Prereqs | C8: SVD & PCA (dimensionality reduction) | D8: SVD: A=UΣVᵀ; singular values = √eigenvalues of AᵀA. Low-rank approximation (Eckart–Young). Why SVD underlies PCA, LSA, embeddings, and LoRA (ΔW is low-rank). PCA: directions of max variance = top eigenvectors of covariance. When PCA fails (nonlinear → t-SNE/UMAP). Truncated SVD for compression. | E8: Derive PCA: maximise wᵀΣw s.t. ‖w‖=1 → eigenvector of covariance (Lagrange multipliers). Show best rank-k approximation = top-k singular triplets (Eckart–Young). Relate SVD of X to eigendecomposition of XᵀX. | F8: Numpy: PCA from scratch (center → covariance → eigh → project to k dims) on a 3D→2D toy set. Verify variance-explained ratio. Compare to np.linalg.svd reconstruction error at rank k. | G8: pca.py + Eckart–Young note | H8: 2 | I8: Not Started | J8: 1
A9: 8 | B9: Stage 1 — Neural Net Foundations | C9: Activation functions (ReLU, GELU, SiLU) | D9: Why ReLU. What GELU approximates. SiLU = x·σ(x). Why dying ReLU happens. | E9: — | F9: Implement ReLU, GELU, SiLU as Python functions. Compute on x=[-2,-1,0,1,2]. Plot. | G9: activations.py + plot | H9: 1 | I9: Not Started | J9: 1
A10: 9 | B10: Stage 1 — Neural Net Foundations | C10: Stable softmax + gradient | D10: Why softmax(x) needs max-subtraction. What overflow looks like. | E10: Derive ∂s_i/∂x_j = s_i(δ_ij − s_j). Verify Jacobian on 3-element example. | F10: Implement numerically stable softmax. Compare to naive on x=[1000,1001,1002]. Backward pass manually. | G10: softmax.py + paper derivation | H10: 2 | I10: Not Started | J10: 1
A11: 10 | B11: Stage 1 — Neural Net Foundations | C11: Cross-Entropy loss + gradient | D11: CE vs log-loss vs log-likelihood (same thing). Why CE is right for classification. | E11: Derive ∂CE/∂logits = softmax − one_hot. (The clean form.) | F11: Implement CE from scratch. Verify against F.cross_entropy. Implement gradient manually. | G11: ce_loss.py + numerical test | H11: 1 | I11: Not Started | J11: 1
A12: 11 | B12: Stage 1 — Neural Net Foundations | C12: Optimizers: SGD → Adam → AdamW | D12: SGD vs momentum vs RMSProp vs Adam vs AdamW. Why decoupled weight decay matters. | E12: Write Adam update rule. Show bias correction. | F12: Implement Adam in numpy. Train your XOR MLP with it. Compare to SGD. | G12: adam.py + comparison plot | H12: 1 | I12: Not Started | J12: 1
A13: 12 | B13: Stage 1 — Neural Net Foundations | C13: Cosine LR + warmup schedule | D13: Why warmup. Why cosine decay. | E13: — | F13: get_lr(step, max_lr, min_lr, warmup, total). Plot curve for warmup=100, total=1000. | G13: lr_schedule.py + plot | H13: 1 | I13: Not Started | J13: 1
... A100: 99 | B100: Stage 16 — Safety, Agents & Company Prep | C100: Company-specific prep (Anthropic/OpenAI/DeepMind/Meta/NVIDIA) | D100: Anthropic: Constitutional AI, RLHF/DPO depth, interpretability, safety framing, 'why Anthropic'. OpenAI: GPT/o-series reasoning, RLHF, scaling laws, function calling, inference opt. DeepMind: Gemini, distributed training, TPU/JAX/XLA, research methodology. Meta: LLaMA, vLLM/PagedAttention, open infra. NVIDIA: CUDA/Triton, FlashAttention internals, TensorRT-LLM, roofline. | E100: — | F100: — | G100: 1-pager per company + 'why team' answers | H100: 2 | I100: Not Started | J100: 1

Sheet Tracker 2 — DSA+SysD+Proj
A1: # | B1: Section | C1: Topic | D1: Task | E1: Deliverable | F1: Hrs | G1: Status | H1: Notes
A2: 1 | B2: DSA — Coding Patterns | C2: Arrays & Two Pointers | D2: NeetCode: Two Sum, 3Sum, Container Water, Trapping Rain Water, Move Zeroes. Time-box 20 min each. | E2: 5 problems solved + patterns noted | F2: 1 | G2: Not Started
A3: 2 | B3: DSA — Coding Patterns | C3: Sliding Window | D3: Longest Substring w/o Repeat, Min Window Substring, Sliding Window Max, Longest Repeating Char Replace. | E3: 4 problems | F3: 1 | G3: Not Started
A4: 3 | B4: DSA — Coding Patterns | C4: Hashing | D4: Group Anagrams, Subarray Sum K, LRU Cache, Longest Consecutive Seq. | E4: 4 problems | F4: 1 | G4: Not Started
A5: 4 | B5: DSA — Coding Patterns | C5: Strings | D5: Valid Palindrome II, Encode/Decode Strings, Longest Palindromic Substring. | E5: 3 problems | F5: 1 | G5: Not Started
A6: 5 | B6: DSA — Coding Patterns | C6: Binary Search | D6: Search Rotated Sorted, Find Peak, Median of 2 Sorted, Koko Bananas. Practice 'search on answer'. | E6: 4 problems | F6: 1 | G6: Not Started
A7: 6 | B7: DSA — Coding Patterns | C7: Stack / Monotonic Stack | D7: Daily Temperatures, Largest Rectangle, Next Greater Element, Min Stack. | E7: 4 problems | F7: 1 | G7: Not Started
A8: 7 | B8: DSA — Coding Patterns | C8: Linked List | D8: Reverse LL, Merge K Sorted, LRU Cache, Copy List with Random Pointer. | E8: 4 problems | F8: 1 | G8: Not Started
A9: 8 | B9: DSA — Coding Patterns | C9: Trees — Traversal | D9: BT Level Order, Serialize/Deserialize BT, LCA, Right Side View. | E9: 4 problems | F9: 1 | G9: Not Started
A10: 9 | B10: DSA — Coding Patterns | C10: Trees — DFS / DP | D10: Max Path Sum, Diameter, House Robber III, All Nodes Distance K. | E10: 4 problems | F10: 1 | G10: Not Started
A11: 10 | B11: DSA — Coding Patterns | C11: Tries | D11: Implement Trie, Word Search II, Design Search Autocomplete. | E11: 3 problems | F11: 1 | G11: Not Started
A12: 11 | B12: DSA — Coding Patterns | C12: Graphs — BFS / DFS | D12: Number of Islands, Clone Graph, Word Ladder, Pacific Atlantic. | E12: 4 problems | F12: 1 | G12: Not Started
A13: 12 | B13: DSA — Coding Patterns | C13: Graphs — Topological Sort | D13: Course Schedule I/II, Alien Dictionary. | E13: 3 problems | F13: 1 | G13: Not Started
... A76: 75 | B76: Behavioral / STAR | C76: Question for interviewer | D76: Prepare 5 thoughtful Qs per company: technical depth, team comp, on-call, growth, recent paper. | E76: 15 Qs prepared | F76: 1 | G76: Not Started

Sheet Inference Engineering
A1: # | B1: Stage | C1: Topic | D1: Theory: read & answer | E1: Math: derive on paper | F1: Code: implement | G1: Deliverable | H1: Hrs | I1: Status | J1: Confidence (1-5) | K1: Notes
A2: 1 | B2: I0 — Foundations & Mental Model | C2: What is LLM inference? Prefill vs decode | D2: Autoregressive generation = one forward pass per token. Two phases: PREFILL (process the whole prompt in parallel, builds the KV cache, produces the 1st token) and DECODE (generate tokens one at a time, each attending to the cache). Why they have totally different performance characteristics. Where the time goes for short vs long prompts. | E2: For prompt length P and G generated tokens, show prefill does ~P tokens of compute once; decode does G sequential steps. Total forward passes = 1 (prefill) + G-1 (decode). | F2: — (draw the prefill→decode timeline and annotate what fills the KV cache at each step) | G2: Prefill/decode timeline diagram | H2: 1 | I2: Not Started | J2: 1
A3: 2 | B3: I0 — Foundations & Mental Model | C3: Latency & throughput metrics (TTFT, TPOT, throughput, goodput) | D3: TTFT (time-to-first-token) = prefill latency, user-perceived responsiveness. TPOT / ITL (inter-token latency) = per-token decode latency, streaming smoothness. E2E latency = TTFT + (G-1)·TPOT. Throughput = tokens/sec across all requests. Goodput = throughput that meets SLO. Why optimizing throughput can hurt TTFT (batching tradeoff). | E3: Write E2E = TTFT + (N_out-1)·TPOT. For TTFT SLO 500ms, TPOT SLO 50ms, 200 output tokens → E2E budget ≈ 10.5s. Show how batch size trades TTFT vs throughput. | F3: Implement a latency calculator: given TTFT, TPOT, output length → E2E; and given per-request latencies + SLOs → goodput fraction. | G3: latency_metrics.py | H3: 1 | I3: Not Started | J3: 1
A4: 3 | B4: I0 — Foundations & Mental Model | C4: The central dichotomy: compute-bound vs memory-bound | D4: The single most important idea in inference. Prefill = compute-bound (lots of matmul, high arithmetic intensity). Decode with batch=1 = memory-bandwidth-bound (you stream all weights from HBM to generate ONE token → GPU compute sits idle). This is why decode throughput scales with batching and with quantization, not with more FLOPs. | E4: Arithmetic intensity AI = FLOPs / bytes_accessed. Show decode batch=1 AI ≈ 0.5 (way below the ridge) → memory-bound. Show prefill AI ≈ S/2 → compute-bound above some S. | F4: — (write the 2-sentence explanation you'd give an interviewer for 'why is LLM decoding slow?') | G4: 60s 'why decode is slow' answer | H4: 1 | I4: Not Started | J4: 1
A5: 4 | B5: I1 — GPU Architecture & Roofline | C5: GPU anatomy: SMs, tensor cores, warps | D5: Streaming Multiprocessors (SMs) = the parallel compute units. Warps = 32 threads executing in lockstep (SIMT). Tensor cores = matmul accelerators (the FLOPS that matter for LLMs). CUDA cores vs tensor cores. Occupancy = active warps / max. Why LLM inference is dominated by GEMMs on tensor cores. | E5: — | F5: — (label a GPU block diagram: SM → warps → tensor/CUDA cores) | G5: GPU anatomy notes | H5: 1 | I5: Not Started | J5: 1
A6: 5 | B6: I1 — GPU Architecture & Roofline | C6: Memory hierarchy & bandwidth (registers → SRAM → L2 → HBM) | D6: Registers (fastest, tiny) → shared memory/SRAM (~KB-MB, per-SM, ~fast) → L2 (MB) → HBM (GB, the big one, the bottleneck). Bandwidth numbers: A100 HBM ≈ 2 TB/s, H100 ≈ 3.35 TB/s; SRAM is ~10-20× faster than HBM. Why FlashAttention exists: keep the n×n scores in SRAM, never write them to HBM. | E6: Compute how long it takes to read 14 GB of fp16 weights from A100 HBM: 14GB / 2TB/s = 7 ms. That is the floor on decode TPOT for a 7B model at batch=1. | F6: — (memory-hierarchy table with capacity + bandwidth per level) | G6: Memory hierarchy table | H6: 1 | I6: Not Started | J6: 1
A7: 6 | B7: I1 — GPU Architecture & Roofline | C7: Roofline model + arithmetic intensity | D7: Roofline: performance is min(peak_FLOPS, AI × peak_bandwidth). The 'ridge point' = peak_FLOPS / peak_BW separates memory-bound (left) from compute-bound (right). A100 ridge ≈ 312 TFLOPS / 2 TB/s = 156 FLOPs/byte. Anything with AI below 156 is memory-bound on A100. This one plot explains all inference optimization. | E7: Compute ridge point for A100 (156) and H100 (~1000 TFLOPS / 3.35 TB/s ≈ 300 FLOPs/byte). Plot where prefill and decode land on the roofline. | F7: Build a roofline_analyzer(flops, bytes, peak_flops, peak_bw) → bound type + achievable FLOPS. Verify it flags decode as memory-bound. | G7: roofline.py + plot | H7: 2 | I7: Not Started | J7: 1
A8: 7 | B8: I1 — GPU Architecture & Roofline | C8: Utilization: MFU vs MBU | D8: MFU (Model FLOPs Utilization) = achieved FLOPs / peak FLOPs — the right metric for compute-bound prefill/training. MBU (Model Bandwidth Utilization) = achieved BW / peak BW — the right metric for memory-bound decode. Why reporting MFU for decode is misleading. Typical real MFU 30-50%, MBU 60-80%. | E8: Given tokens/sec and model size, back out MBU = (params·bytes·tokens_per_sec)/peak_BW. Compute MBU for 7B fp16 at 140 tok/s on A100. | F8: — (add MFU/MBU output to your roofline tool) | G8: MFU/MBU notes | H8: 1 | I8: Not Started | J8: 1
A9: 8 | B9: I1 — GPU Architecture & Roofline | C9: Numeric formats: FP32/TF32/FP16/BF16/FP8/INT8/INT4 | D9: Bytes per param and dynamic range/precision tradeoffs. FP16 (5-exp) vs BF16 (8-exp, no loss scaling) vs FP8 E4M3/E5M2 (Hopper) vs INT8/INT4 (integer, needs scale). Why weights in low precision cut both memory AND bandwidth → directly speeds up memory-bound decode. Accuracy cliffs. | E9: Tabulate bytes/param and represent-able range for each format. Show a 70B model: fp16=140GB, int8=70GB, int4=35GB → which fit on 1×/2×/8× 80GB GPUs. | F9: — (precision comparison table) | G9: Precision table | H9: 1 | I9: Not Started | J9: 1
A10: 9 | B10: I2 — Transformer Inference Math | C10: FLOP counting for a forward pass | D10: A (M×K)·(K×N) GEMM = 2·M·K·N FLOPs. Forward pass ≈ 2·N·D FLOPs per token (N=params, D=tokens). Per-layer breakdown: QKV proj, attention scores, AV, output proj, FFN (dominant). Backward ≈ 2× forward, so training ≈ 6ND; inference forward-only ≈ 2ND. | E10: Count FLOPs per op for one transformer layer (d_model, n_heads, seq S). Sum over L layers. Verify total ≈ 2·N per token within 5% for GPT-2 small. | F10: flop_counter(L,D,H,S,vocab) for the forward pass; test on LLaMA-7B at S=2048. | G10: flop_counter.py | H10: 2 | I10: Not Started | J10: 1
A11: 10 | B11: I2 — Transformer Inference Math | C11: TTFT (prefill) estimation | D11: Prefill is compute-bound: process all S prompt tokens in parallel. TTFT ≈ prefill_FLOPs / (peak_FLOPS · MFU). Scales ~linearly with prompt length (quadratically for the attention term at long context). Batching prompts increases throughput but each TTFT grows. | E11: TTFT ≈ (2·N·S)/(FLOPS·MFU). Compute TTFT for 7B, S=512, A100 (312 TFLOPS, 50% MFU) ≈ 12·L·D²·S/FLOPS. Show the long-context S² attention term overtaking. | F11: Add ttft_estimate() to your latency tool; compare to a measured vLLM prefill within 20%. | G11: ttft.py + validation | H11: 1 | I11: Not Started | J11: 1
A12: 11 | B12: I2 — Transformer Inference Math | C12: TPOT (decode) estimation | D12: Decode at batch=1 is bandwidth-bound: TPOT ≈ weights_bytes / (peak_BW · MBU). Independent of prompt length (KV read is small vs weights) until context is huge. Increasing batch amortizes the weight read across many sequences → higher throughput, same-ish TPOT until compute-bound. | E12: TPOT ≈ model_bytes / GPU_BW. 7B fp16 on A100 = 14GB/2TB/s = 7ms/tok. 70B fp16 TP=4 on A100 = (140/4)GB / 2TB/s ≈ 17.5ms/tok. Find the batch size where decode turns compute-bound. | F12: tpot_estimate(model_bytes, bw, batch); verify the 7B and 70B cases. | G12: tpot.py | H12: 2 | I12: Not Started | J12: 1
A13: 12 | B13: I2 — Transformer Inference Math | C13: Inference memory footprint: weights + KV + activations | D13: Inference memory = weights (2P fp16) + KV cache (grows with batch × seq) + activations (small, transient) + framework overhead. Unlike training (16P for optimizer states), inference weights are just 2P. At scale the KV cache, not the weights, is what caps concurrency. | E13: Total = 2P + KV(batch,seq) + overhead. For 7B fp16: 14GB weights; at batch=32, seq=2048 KV can be another ~8-16GB. Compute max concurrent sequences on an 80GB GPU. | F13: llm_infer_memory(params_B, dtype, batch, seq, layers, kv_heads, d_head) → GB breakdown. | G13: infer_mem.py + cases | H13: 2 | I13: Not Started | J13: 1
... A54: 53 | B54: I12 — Capstone & Synthesis | C54: Inference formulas & key numbers — from memory | D54: Re-write every core inference formula cold: roofline/ridge, arithmetic intensity, KV-cache bytes, TTFT, TPOT, FlashAttention IO, PagedAttention waste, GQA reduction, spec-decoding speedup, cost/token. Plus key hardware numbers (A100/H100 FLOPS + BW). The pre-interview cheat sheet. | E54: Reproduce all formulas + the A100/H100 numbers from memory; redo monthly. | F54: — | G54: Inference cheat sheet recreated | H54: 1 | I54: Not Started | J54: 1

Sheet Fine-Tuning
A1: # | B1: Stage | C1: Topic | D1: Theory: read & answer | E1: Math: derive on paper | F1: Code: implement | G1: Deliverable | H1: Hrs | I1: Status | J1: Confidence (1-5) | K1: Notes
A2: 1 | B2: F0 — Landscape & Mental Model | C2: The full post-training pipeline | D2: The canonical modern recipe: pretrain (next-token) → SFT (instruction following) → preference optimization (RLHF/PPO or DPO) → optional iterative rounds. What each stage buys: SFT teaches format/behavior, preference tuning teaches ranking/values. Base vs instruct vs chat models. Where your voice-bot SFT+DPO pipeline sits. | E2: — | F2: — (draw the pretrain→SFT→preference→eval pipeline; annotate what data + loss each stage uses) | G2: Pipeline diagram + 60s explainer | H2: 1 | I2: Not Started | J2: 1
A3: 2 | B3: F0 — Landscape & Mental Model | C3: When to fine-tune vs RAG vs prompt vs pretrain | D3: Decision framework: prompt engineering (fast, no data) → RAG (inject knowledge, reduce hallucination) → fine-tune (change behavior/format/style, distill) → continued pretrain (new domain/language). Cost, latency, data, and maintenance tradeoffs. Fine-tuning teaches BEHAVIOR, not FACTS — the key interview line. | E3: — | F3: — (build the decision table + a crisp 90s 'when would you fine-tune vs RAG vs prompt' answer) | G3: Decision framework rehearsed | H3: 1 | I3: Not Started | J3: 1
A4: 3 | B4: F0 — Landscape & Mental Model | C4: Full fine-tune vs PEFT — the framework | D4: Full FT (update all params) vs PEFT (LoRA/adapters, update <1%). Compute, memory, catastrophic forgetting, multi-task/multi-adapter serving, generalization. When full FT is actually worth it (large domain shift, you own the base). Why PEFT dominates in practice. | E4: Contrast trainable params + optimizer memory: full FT 7B = 16P bytes ≈ 112GB; LoRA r=16 ≈ 0.6% trainable, adapter optimizer state tiny. | F4: — (comparison table: full FT vs LoRA vs QLoRA across compute/memory/quality/serving) | G4: Full-FT-vs-PEFT table | H4: 1 | I4: Not Started | J4: 1
A5: 4 | B5: F1 — Data (the real bottleneck) | C5: SFT data format & chat templates | D5: Instruction/response format. Chat templates (system/user/assistant roles, special tokens like <|im_start|>). Why the template MUST match training and inference exactly (mismatch = silent quality loss — your Gemma chat-template fix). Multi-turn formatting. Tool-call formatting. | E5: — | F5: Implement a chat-template tokenizer: render a multi-turn conversation into token ids with correct role markers; verify round-trip decode. | G5: chat_template.py + round-trip test | H5: 2 | I5: Not Started | J5: 1
A6: 5 | B6: F1 — Data (the real bottleneck) | C6: Loss masking (the #1 SFT bug) | D6: Only ASSISTANT tokens contribute to loss; prompt/user/system tokens get label = -100 (ignored). Why: you don't want the model learning to generate the user's turns. What happens if you don't mask (model degrades, learns to echo prompts). Completion-only vs full-sequence loss. | E6: Show the loss is L = -(1/N_assistant) Σ over assistant tokens only. Demonstrate why including prompt tokens biases the gradient. | F6: Build labels with -100 masking for a multi-turn sample; verify only assistant tokens have non-ignored labels and contribute to CE. | G6: loss_mask.py + verification | H6: 2 | I6: Not Started | J6: 1
A7: 6 | B7: F1 — Data (the real bottleneck) | C7: Data quality, quantity & curation (LIMA, quality>quantity) | D7: LIMA: 1k high-quality examples beat 50k noisy ones — 'less is more for alignment'. Diversity, deduplication, difficulty balance. Synthetic data (Self-Instruct, Evol-Instruct, distillation from a stronger model). Data contamination / eval leakage. How much data SFT actually needs. | E7: — | F7: — (write a data-quality checklist + a dedup/near-dup detection sketch) | G7: Data curation notes + checklist | H7: 1 | I7: Not Started | J7: 1
A8: 7 | B8: F1 — Data (the real bottleneck) | C8: Preference data (chosen/rejected pairs) | D8: Format for RLHF/DPO: (prompt, chosen, rejected). How pairs are collected: human ranking, AI feedback (RLAIF), model-vs-model, best-of-n. Inter-annotator agreement. Noise and its effect. On-policy vs off-policy preference data. Why pair quality caps preference-tuning quality. | E8: — | F8: — (design a preference-collection scheme for your voice bot; note agreement + noise handling) | G8: Preference-data design notes | H8: 1 | I8: Not Started | J8: 1
A9: 8 | B9: F1 — Data (the real bottleneck) | C9: Packing, padding, truncation & masking mechanics | D9: Sequence packing (concatenate short samples to fill context, with attention resets so samples don't attend across boundaries) vs padding. Truncation strategy (keep the response). Attention masks. Throughput impact of packing. Position-id resets. | E9: Show packing efficiency gain = 1 - (padded_tokens/total). Compute for a batch with high length variance. | F9: Implement sequence packing with a block-diagonal attention mask + position-id reset; verify samples don't attend across boundaries. | G9: packing.py + mask test | H9: 1 | I9: Not Started | J9: 1
A10: 9 | B10: F2 — SFT (Supervised Fine-Tuning) | C10: SFT objective & the training loop | D10: SFT = causal LM cross-entropy on (masked) assistant tokens. The full loop: forward → CE on assistant tokens → backward → optimizer step. Teacher forcing. Why SFT alone can't exceed the quality of its demonstrations (imitation ceiling) → motivates preference tuning. | E10: Write L_SFT = -Σ_t m_t · log π_θ(y_t | y_<t, x), m_t = assistant mask. Relate to MLE. | F10: Full SFT loop on a tiny model: masked CE, AdamW, cosine LR + warmup, grad clip; log loss. Verify loss decreases and only assistant tokens train. | G10: sft_train.py + loss curve | H10: 2 | I10: Not Started | J10: 1
A11: 10 | B11: F2 — SFT (Supervised Fine-Tuning) | C11: Hyperparameters that matter (LR, epochs, warmup) | D11: Learning rate (SFT typically 1e-5 to 2e-5 full, higher for LoRA), 1-3 epochs (more → overfit/forget), warmup ratio, cosine vs linear decay, batch size + grad accumulation, weight decay, NEFTune noise. How to tell you're overfitting (train loss ↓ but eval/behavior ↓). | E11: Effective batch = micro_batch × grad_accum × n_gpu. Compute the accum steps to hit a target effective batch on limited memory. | F11: Add gradient accumulation to your SFT loop; verify effective batch matches the non-accumulated run's gradients. | G11: grad_accum.py + hp notes | H11: 1 | I11: Not Started | J11: 1
A12: 11 | B12: F2 — SFT (Supervised Fine-Tuning) | C12: Catastrophic forgetting & mitigation | D12: Fine-tuning erodes pretrained capabilities. Mitigations: lower LR, fewer epochs, LoRA (freezes base), replay/mixing pretrain data, KL/regularization to base, model averaging (model soup / WiSE-FT). How to measure forgetting (eval on general benchmarks before/after). | E12: Show LoRA limits forgetting because base weights are frozen; contrast with full FT weight drift ‖θ_ft - θ_base‖. | F12: — (measure a general-capability proxy before/after a fine-tune; note the drop) | G12: Forgetting notes + measurement | H12: 1 | I12: Not Started | J12: 1
A13: 12 | B13: F3 — PEFT (LoRA & Family) | C13: LoRA — math (ΔW=BA, α/r scaling, ΔW=0 init) | D13: ΔW = BA, B∈R^{d×r}, A∈R^{r×k}, r ≪ d. Forward: h = W₀x + (α/r)·BAx. Init A~N(0,σ²), B=0 so ΔW=0 at start (training begins from the pretrained model). α/r scaling decouples LR from rank. Low intrinsic-rank hypothesis. Which modules to target (q,k,v,o + MLP). | E13: Show BA=0 at init and becomes nonzero after one gradient step. LoRA params = r·(d_in+d_out). For 7B all-linear r=16 ≈ 0.6% trainable. Show α/r scaling effect on update magnitude. | F13: LoRALinear: freeze base, add A,B with α/r scaling; merge_weights() folds ΔW into W₀. Apply to attention+FFN; verify <2% trainable, only adapters in optimizer. | G13: lora.py + merge fn | H13: 2 | I13: Not Started | J13: 1
... A53: 52 | B53: F10 — Evaluation & Synthesis | C53: Fine-tuning formulas & cold re-implementations | D53: Re-derive/re-implement cold, no notes, under time: SFT masked loss, LoRA (ΔW=BA, α/r), DPO loss + full derivation, BT reward loss, RLHF objective + π*, PPO clip + GAE, GRPO advantage, InfoNCE. The pre-interview confidence test for the whole fine-tuning stack. | E53: Reproduce every formula above from memory; redo the DPO derivation cold. | F53: Cold re-impl (<20 min each, no notes): LoRA, DPO loss, BT loss, PPO clip. | G53: Timed cold re-dos + cheat sheet | H53: 2 | I53: Not Started | J53: 1

Sheet Dashboard
A1: INTERVIEW PREP — PROGRESS DASHBOARD
A3: Tracker 1 — LLM Learning
A4: Total | B4: 99
A5: Done | B5: =COUNTIF('Tracker 1 — LLM Learning'!I:I,"Done")
A6: In Progress | B6: =COUNTIF('Tracker 1 — LLM Learning'!I:I,"In Progress")
A7: % Complete | B7: =IFERROR(B5/B4,0)
A9: Tracker 2 — DSA + System Design + Projects
A10: Total | B10: 75
A11: Done | B11: =COUNTIF('Tracker 2 — DSA+SysD+Proj'!G:G,"Done")
A12: In Progress | B12: =COUNTIF('Tracker 2 — DSA+SysD+Proj'!G:G,"In Progress")
A13: % Complete | B13: =IFERROR(B11/B10,0)
A15: Tracker 1 by Stage
A16: Stage | B16: Total | C16: Done | D16: %
A17: Stage 0 — Math & ML Prereqs | B17: =COUNTIF('Tracker 1 — LLM Learning'!B:B,A17) | C17: =COUNTIFS('Tracker 1 — LLM Learning'!B:B,A17,'Tracker 1 — LLM Learning'!I:I,"Done") | D17: =IFERROR(C17/B17,0)
A18: Stage 1 — Neural Net Foundations | B18: =COUNTIF('Tracker 1 — LLM Learning'!B:B,A18) | C18: =COUNTIFS('Tracker 1 — LLM Learning'!B:B,A18,'Tracker 1 — LLM Learning'!I:I,"Done") | D18: =IFERROR(C18/B18,0)
A19: Stage 2 — Tokenization & Embeddings | B19: =COUNTIF('Tracker 1 — LLM Learning'!B:B,A19) | C19: =COUNTIFS('Tracker 1 — LLM Learning'!B:B,A19,'Tracker 1 — LLM Learning'!I:I,"Done") | D19: =IFERROR(C19/B19,0)
A20: Stage 3 — Attention (the core) | B20: =COUNTIF('Tracker 1 — LLM Learning'!B:B,A20) | C20: =COUNTIFS('Tracker 1 — LLM Learning'!B:B,A20,'Tracker 1 — LLM Learning'!I:I,"Done") | D20: =IFERROR(C20/B20,0)
A21: Stage 4 — Positional Encoding | B21: =COUNTIF('Tracker 1 — LLM Learning'!B:B,A21) | C21: =COUNTIFS('Tracker 1 — LLM Learning'!B:B,A21,'Tracker 1 — LLM Learning'!I:I,"Done") | D21: =IFERROR(C21/B21,0)
A22: Stage 5 — Transformer Block | B22: =COUNTIF('Tracker 1 — LLM Learning'!B:B,A22) | C22: =COUNTIFS('Tracker 1 — LLM Learning'!B:B,A22,'Tracker 1 — LLM Learning'!I:I,"Done") | D22: =IFERROR(C22/B22,0)
A23: Stage 6 — GPT / Decoder | B23: =COUNTIF('Tracker 1 — LLM Learning'!B:B,A23) | C23: =COUNTIFS('Tracker 1 — LLM Learning'!B:B,A23,'Tracker 1 — LLM Learning'!I:I,"Done") | D23: =IFERROR(C23/B23,0)
A24: Stage 7 — Efficient Attention | B24: =COUNTIF('Tracker 1 — LLM Learning'!B:B,A24) | C24: =COUNTIFS('Tracker 1 — LLM Learning'!B:B,A24,'Tracker 1 — LLM Learning'!I:I,"Done") | D24: =IFERROR(C24/B24,0)
A25: Stage 8 — Training at Scale | B25: =COUNTIF('Tracker 1 — LLM Learning'!B:B,A25) | C25: =COUNTIFS('Tracker 1 — LLM Learning'!B:B,A25,'Tracker 1 — LLM Learning'!I:I,"Done") | D25: =IFERROR(C25/B25,0)
A26: Stage 9 — Fine-Tuning / PEFT | B26: =COUNTIF('Tracker 1 — LLM Learning'!B:B,A26) | C26: =COUNTIFS('Tracker 1 — LLM Learning'!B:B,A26,'Tracker 1 — LLM Learning'!I:I,"Done") | D26: =IFERROR(C26/B26,0)
A27: Stage 10 — Alignment (RLHF / DPO) | B27: =COUNTIF('Tracker 1 — LLM Learning'!B:B,A27) | C27: =COUNTIFS('Tracker 1 — LLM Learning'!B:B,A27,'Tracker 1 — LLM Learning'!I:I,"Done") | D27: =IFERROR(C27/B27,0)
A28: Stage 11 — Quantization & Inference | B28: =COUNTIF('Tracker 1 — LLM Learning'!B:B,A28) | C28: =COUNTIFS('Tracker 1 — LLM Learning'!B:B,A28,'Tracker 1 — LLM Learning'!I:I,"Done") | D28: =IFERROR(C28/B28,0)
... A33: Stage 16 — Safety, Agents & Company Prep | B33: =COUNTIF('Tracker 1 — LLM Learning'!B:B,A33) | C33: =COUNTIFS('Tracker 1 — LLM Learning'!B:B,A33,'Tracker 1 — LLM Learning'!I:I,"Done") | D33: =IFERROR(C33/B33,0)
A34: Tracker 2 by Section
A35: Section | B35: Total | C35: Done | D35: %
A36: DSA — Coding Patterns | B36: =COUNTIF('Tracker 2 — DSA+SysD+Proj'!B:B,A36) | C36: =COUNTIFS('Tracker 2 — DSA+SysD+Proj'!B:B,A36,'Tracker 2 — DSA+SysD+Proj'!G:G,"Done") | D36: =IFERROR(C36/B36,0)
A37: System Design | B37: =COUNTIF('Tracker 2 — DSA+SysD+Proj'!B:B,A37) | C37: =COUNTIFS('Tracker 2 — DSA+SysD+Proj'!B:B,A37,'Tracker 2 — DSA+SysD+Proj'!G:G,"Done") | D37: =IFERROR(C37/B37,0)
A38: Projects — Q&A & STAR | B38: =COUNTIF('Tracker 2 — DSA+SysD+Proj'!B:B,A38) | C38: =COUNTIFS('Tracker 2 — DSA+SysD+Proj'!B:B,A38,'Tracker 2 — DSA+SysD+Proj'!G:G,"Done") | D38: =IFERROR(C38/B38,0)
A39: Behavioral / STAR | B39: =COUNTIF('Tracker 2 — DSA+SysD+Proj'!B:B,A39) | C39: =COUNTIFS('Tracker 2 — DSA+SysD+Proj'!B:B,A39,'Tracker 2 — DSA+SysD+Proj'!G:G,"Done") | D39: =IFERROR(C39/B39,0)

Sheet Formulas
A1: Category | B1: Name | C1: Formula | D1: Intuition / Key Numbers | E1: Priority
A2: ATTENTION | B2: Scaled Dot-Product | C2: softmax(QKᵀ/√d_k)·V | D2: √d_k prevents softmax saturation. O(n²d). Causal mask -inf. | E2: ⭐⭐⭐
A3: ATTENTION | B3: MHA Parameters | C3: 4·d_model² per layer | D3: GPT-3 d=12288, 96 layers → ~70B in attention. | E3: ⭐⭐⭐
A4: ATTENTION | B4: KV Cache Memory | C4: 2·L·S·G·d_h·dtype | D4: LLaMA-2 70B (L=80,G=8,d_h=128,S=4096,fp16) = 10.5GB/batch item. | E4: ⭐⭐⭐
A5: ATTENTION | B5: GQA KV Reduction | C5: MHA/GQA = H/G | D5: LLaMA-2 70B 64Q/8KV → 8× reduction. | E5: ⭐⭐
A6: POSITION | B6: RoPE | C6: q_m = q·e^(imΘ), Θ_j = base^(-2j/d) | D6: Relative pos in QKᵀ. base=10000, LLaMA-3=500000. | E6: ⭐⭐⭐
A7: POSITION | B7: NTK Context Scaling | C7: θ_new = θ_old·(L_test/L_train)^(d/(d-2)) | D7: LLaMA-2 4096→32k: new_base ≈ 136k. | E7: ⭐⭐
A8: POSITION | B8: ALiBi | C8: score = q·k/√d_k − m_h·(i−j) | D8: m_h = 2^(-8h/n). Zero-shot length generalization. | E8: ⭐⭐
A9: NORMS | B9: LayerNorm | C9: γ·(x−μ)/√(σ²+ε) + β | D9: Bwd: (γ/σ)·[dL/dy − mean(dL/dy) − x̂·mean(dL/dy·x̂)]. | E9: ⭐⭐⭐
A10: NORMS | B10: RMSNorm | C10: γ·x/RMS(x), RMS=√mean(x²) | D10: No mean subtraction. LLaMA/Mistral/Gemma. | E10: ⭐⭐⭐
A11: FFN | B11: SwiGLU | C11: (xW₁ ⊙ SiLU(xW_gate))·W₂ | D11: 3 matrices; 8/3·d hidden for same param count. | E11: ⭐⭐
A12: TRAINING | B12: CLM Loss + PPL | C12: L = -1/N·Σ log P(x_i+1|x_1..i), PPL=exp(L) | D12: PPL=10 ⇒ confused among 10 options. | E12: ⭐⭐⭐
... A29: A/B TEST | B29: Sample size | C29: n = (z_{α/2}+z_β)²·2σ²/Δ² | D29: MDE, α, β determine n. Asked at LinkedIn. | E29: ⭐⭐⭐

Sheet Mocks
A1: # | B1: Mock | C1: Format | D1: Platform | E1: When | F1: Status | G1: Score /5 | H1: Notes
A2: 1 | B2: DSA + ML Concepts | C2: 45 min DSA (2 mediums) + 30 min verbal ML | D2: Pramp / peer | E2: After Tracker 1 Stage 3 | F2: Not Started
A3: 2 | B3: ML System Design | C3: 45 min: voice AI or YouTube recs | D3: Interviewing.io / peer | E3: After Tracker 2 SysD #4 | F3: Not Started
A4: 3 | B4: ML Fundamentals Depth | C4: 45 min: derive attention, explain DPO, critique eval | D4: Peer | E4: After Tracker 1 Stage 10 | F4: Not Started
A5: 4 | B5: Full FAANG Loop sim | C5: 45 DSA + 45 sysdesign + 20 behavioral | D5: Interviewing.io | E5: After 50% on both trackers | F5: Not Started
A6: 5 | B6: Coding Speed Run | C6: 60 min: 2 mediums + 1 hard NeetCode. Record. | D6: Self / peer | E6: Mid-prep | F6: Not Started
A7: 6 | B7: Full Loop Dress Rehearsal | C7: 3 hours: DSA + sysdesign + ML + behavioral | D7: Interviewing.io | E7: Final week before loops | F7: Not Started
A8: 7 | B8: Google Coding Phone Screen Sim | C8: 45 min, 1 med + 1 med-hard. Verbalize. | D8: Pramp / peer | E8: Pre-Google onsite | F8: Not Started
A9: 8 | B9: Google Coding Onsite Sim | C9: 45 min, 1 hard + follow-up | D9: Pramp / peer | E9: Pre-Google onsite | F9: Not Started
A10: 9 | B10: Google ML Domain | C10: 45 min: classical + DL + debugging scenario | D10: Peer | E10: Pre-Google onsite | F10: Not Started
A11: 10 | B11: Google ML System Design (product) | C11: 45 min: YouTube recs or Ads CTR. Whiteboard. | D11: Peer | E11: Pre-Google onsite | F11: Not Started
A12: 11 | B12: Google Behavioral / Googlyness | C12: 45 min: 5-6 STAR questions | D12: Peer | E12: Pre-Google onsite | F12: Not Started

Sheet Applications
A1: # | B1: Company | C1: Role | D1: Applied Date | E1: Source | F1: Status | G1: Recruiter / Contact | H1: Next Action / Notes
A2: 1
A3: 2
A4: 3
A5: 4
A6: 5
A7: 6
A8: 7
A9: 8
A10: 9
A11: 10
A12: 11
A13: 12
... A51: 50
